Metadata-Version: 2.1
Name: behave-no-capture
Version: 1.2.7.dev2
Summary: behave is behaviour-driven development, Python style
Home-page: http://github.com/behave/behave
Author: Jens Engel, Benno Rice and Richard Jones
Author-email: behave-users@googlegroups.com
License: BSD
Platform: UNKNOWN
Classifier: Development Status :: 4 - Beta
Classifier: Environment :: Console
Classifier: Intended Audience :: Developers
Classifier: Operating System :: OS Independent
Classifier: Programming Language :: Python :: 2
Classifier: Programming Language :: Python :: 2.7
Classifier: Programming Language :: Python :: 3
Classifier: Programming Language :: Python :: 3.5
Classifier: Programming Language :: Python :: 3.6
Classifier: Programming Language :: Python :: 3.7
Classifier: Programming Language :: Python :: 3.8
Classifier: Programming Language :: Python :: 3.9
Classifier: Programming Language :: Python :: 3.10
Classifier: Programming Language :: Python :: Implementation :: CPython
Classifier: Programming Language :: Python :: Implementation :: Jython
Classifier: Programming Language :: Python :: Implementation :: PyPy
Classifier: Topic :: Software Development :: Testing
Classifier: License :: OSI Approved :: BSD License
Provides: behave
Provides: setuptools_behave
Requires-Python: >=2.7, !=3.0.*, !=3.1.*, !=3.2.*
License-File: LICENSE
Requires-Dist: cucumber-tag-expressions (>=4.1.0)
Requires-Dist: parse (>=1.18.0)
Requires-Dist: parse-type (>=0.6.0)
Requires-Dist: six (>=1.15.0)
Requires-Dist: colorama (>=0.3.7)
Requires-Dist: traceback2 ; python_version < "3.0"
Requires-Dist: enum34 ; python_version < "3.4"
Requires-Dist: contextlib2 ; python_version < "3.5"
Requires-Dist: win-unicode-console ; python_version <= "3.9"
Provides-Extra: develop
Requires-Dist: coverage ; extra == 'develop'
Requires-Dist: pytest-cov ; extra == 'develop'
Requires-Dist: tox ; extra == 'develop'
Requires-Dist: invoke (>=1.4.0) ; extra == 'develop'
Requires-Dist: pycmd ; extra == 'develop'
Requires-Dist: modernize (>=0.5) ; extra == 'develop'
Requires-Dist: pylint ; extra == 'develop'
Requires-Dist: pytest (<5.0,>=4.2) ; (python_version < "3.0") and extra == 'develop'
Requires-Dist: pytest-html (<2.0,>=1.19.0) ; (python_version < "3.0") and extra == 'develop'
Requires-Dist: PyHamcrest (<2.0) ; (python_version < "3.0") and extra == 'develop'
Requires-Dist: path.py (>=11.5.0) ; (python_version < "3.5") and extra == 'develop'
Requires-Dist: mock (<4.0) ; (python_version < "3.6") and extra == 'develop'
Requires-Dist: pathlib ; (python_version <= "3.4") and extra == 'develop'
Requires-Dist: pytest (>=5.0) ; (python_version >= "3.0") and extra == 'develop'
Requires-Dist: pytest-html (>=2.0) ; (python_version >= "3.0") and extra == 'develop'
Requires-Dist: PyHamcrest (>=2.0.2) ; (python_version >= "3.0") and extra == 'develop'
Requires-Dist: path (>=13.1.0) ; (python_version >= "3.5") and extra == 'develop'
Requires-Dist: mock (>=4.0) ; (python_version >= "3.6") and extra == 'develop'
Provides-Extra: docs
Requires-Dist: sphinx (>=1.6) ; extra == 'docs'
Requires-Dist: sphinx-bootstrap-theme (>=0.6) ; extra == 'docs'
Provides-Extra: formatters
Requires-Dist: behave-html-formatter ; extra == 'formatters'
